mitzu/.DS_Store
mitzu/__init__.py
mitzu/adapters/__init__.py
mitzu/adapters/adapter_factory.py
mitzu/adapters/athena_adapter.py
mitzu/adapters/bigquery_adapter.py
mitzu/adapters/databricks_adapter.py
mitzu/adapters/file_adapter.py
mitzu/adapters/generic_adapter.py
mitzu/adapters/helper.py
mitzu/adapters/mysql_adapter.py
mitzu/adapters/postgresql_adapter.py
mitzu/adapters/redshift_adapter.py
mitzu/adapters/snowflake_adapter.py
mitzu/adapters/sqlalchemy/__init__.py
mitzu/adapters/sqlalchemy/athena/__init__.py
mitzu/adapters/sqlalchemy/athena/sqlalchemy/__init__.py
mitzu/adapters/sqlalchemy/athena/sqlalchemy/compiler.py
mitzu/adapters/sqlalchemy/athena/sqlalchemy/datatype.py
mitzu/adapters/sqlalchemy/athena/sqlalchemy/dialect.py
mitzu/adapters/sqlalchemy/athena/sqlalchemy/error.py
mitzu/adapters/sqlalchemy/bigquery/__init__.py
mitzu/adapters/sqlalchemy/bigquery/sqlalchemy/__init__.py
mitzu/adapters/sqlalchemy/bigquery/sqlalchemy/_helpers.py
mitzu/adapters/sqlalchemy/bigquery/sqlalchemy/_struct.py
mitzu/adapters/sqlalchemy/bigquery/sqlalchemy/_types.py
mitzu/adapters/sqlalchemy/bigquery/sqlalchemy/dialect.py
mitzu/adapters/sqlalchemy/bigquery/sqlalchemy/geography.py
mitzu/adapters/sqlalchemy/bigquery/sqlalchemy/parse_url.py
mitzu/adapters/sqlalchemy/bigquery/sqlalchemy/requirements.py
mitzu/adapters/sqlalchemy/bigquery/sqlalchemy/version.py
mitzu/adapters/sqlalchemy/databricks/__init__.py
mitzu/adapters/sqlalchemy/databricks/sqlalchemy/__init__.py
mitzu/adapters/sqlalchemy/databricks/sqlalchemy/compiler.py
mitzu/adapters/sqlalchemy/databricks/sqlalchemy/datatype.py
mitzu/adapters/sqlalchemy/databricks/sqlalchemy/dialect.py
mitzu/adapters/sqlalchemy/databricks/sqlalchemy/error.py
mitzu/adapters/sqlalchemy_adapter.py
mitzu/adapters/sqlite_adapter.py
mitzu/adapters/trino_adapter.py
mitzu/helper.py
mitzu/model.py
mitzu/notebook/__init__.py
mitzu/notebook/model_loader.py
mitzu/project_discovery.py
mitzu/project_serialization.py
mitzu/samples/__init__.py
mitzu-0.6.11.dist-info/LICENSE.txt
mitzu-0.6.11.dist-info/METADATA
mitzu-0.6.11.dist-info/WHEEL
mitzu-0.6.11.dist-info/RECORD
